.travis.yml
MANIFEST.in
README.rst
requirements-devel.pip
setup.py
tox.ini
NativeImaging/__init__.py
NativeImaging/api.py
NativeImaging.egg-info/PKG-INFO
NativeImaging.egg-info/SOURCES.txt
NativeImaging.egg-info/dependency_links.txt
NativeImaging.egg-info/top_level.txt
NativeImaging/backends/GraphicsMagick.py
NativeImaging/backends/__init__.py
NativeImaging/backends/aware.py
NativeImaging/backends/java.py
NativeImaging/backends/wand_wrapper.py
doc/Makefile
doc/api.rst
doc/conf.py
doc/index.rst
doc/backends/aware.rst
doc/backends/graphicsmagick.rst
doc/backends/java.rst
tests/__init__.py
tests/api.py
tests/resize-bench.py
tests/test_aware.py
tests/test_graphicsmagick.py
tests/test_java.py
tests/test_pil.py
tests/samples/.gitignore
tests/samples/4160452059_c7757f89d1_o.jpg
tests/samples/5071384885_c5f331d337_b.jpg
tests/samples/g8960_ct000508.png
tests/samples/g8960_ct000508.tif
tests/samples/leaves.jp2
tests/samples/m83_hst_big.jpg