Metadata-Version: 1.0
Name: NativeImaging
Version: 0.0.10
Summary: PIL-like interface for system imaging libraries
Home-page: http://github.com/acdha/NativeImaging/
Author: Chris Adams
Author-email: chris@improbable.org
License: http://www.opensource.org/licenses/mit-license.php
Platform: UNKNOWN
